{
    "genres": [
        "Hip-Hop", 
        "Christian Rap", 
        "rap", 
        "electronica", 
        "breakbeat"
    ], 
    "taskDuration": {
        "Task Duration": 3.696254014968872, 
        "Task End": 1564714016.21569, 
        "Task Start": 1564714012.519436
    }, 
    "stats": {
        "listeners": "1493", 
        "playcount": "8896"
    }, 
    "name": "E-Roc", 
    "mbid": "57b28f16-22ac-45a2-a866-58d6f65a087b", 
    "birthday": null, 
    "date": "2019-08-01", 
    "albums": [
        {
            "mbid": "a1705088-7b0c-4382-acd1-ccb1366344d5", 
            "releases": [], 
            "title": "Avalanche"
        }, 
        {
            "mbid": "e6fd8dfe-08b5-4ba2-ada6-11d51d998e9a", 
            "releases": [], 
            "title": "Greatest Hits"
        }
    ], 
    "type": "Person"
}